infoblox_netmri/__init__.py
infoblox_netmri/client.py
infoblox_netmri-0.1.5.dist-info/DESCRIPTION.rst
infoblox_netmri-0.1.5.dist-info/METADATA
infoblox_netmri-0.1.5.dist-info/RECORD
infoblox_netmri-0.1.5.dist-info/WHEEL
infoblox_netmri-0.1.5.dist-info/metadata.json
infoblox_netmri-0.1.5.dist-info/top_level.txt
