Metadata-Version: 2.0
Name: infoblox-netmri
Version: 0.1.5
Summary: A simple client for the Infoblox NetMRI RESTful API.
Home-page: https://github.com/infobloxopen/infoblox-netmri
Author: John Belamaric
Author-email: jbelamaric@infoblox.com
License: Apache
Keywords: infoblox_netmri netmri infoblox network automation
Platform: UNKNOWN
Classifier: Development Status :: 4 - Beta
Classifier: Intended Audience :: Developers
Classifier: License :: OSI Approved :: Apache Software License
Classifier: Natural Language :: English
Classifier: Programming Language :: Python :: 2
Classifier: Programming Language :: Python :: 2.6
Classifier: Programming Language :: Python :: 2.7
Classifier: Programming Language :: Python :: 3
Classifier: Programming Language :: Python :: 3.4
Requires-Dist: requests (>=2.5.2)
